aecf/AECFLayer.py
aecf/__init__.py
aecf/py.typed
aecf-0.1.0.dist-info/licenses/LICENSE
aecf-0.1.0.dist-info/METADATA
aecf-0.1.0.dist-info/WHEEL
aecf-0.1.0.dist-info/top_level.txt
aecf-0.1.0.dist-info/RECORD
