Metadata-Version: 2.4
Name: aecf
Version: 0.1.0
Summary: Adaptive Entropy-Gated Contrastive Fusion for robust multimodal learning
Home-page: https://github.com/your-username/aecf
Author: Your Name
Author-email: Your Name <your.email@example.com>
License-Expression: MIT
Project-URL: Homepage, https://github.com/your-username/aecf
Project-URL: Repository, https://github.com/your-username/aecf
Project-URL: Documentation, https://github.com/your-username/aecf#readme
Project-URL: Bug Reports, https://github.com/your-username/aecf/issues
Project-URL: Paper, https://arxiv.org/abs/2505.15417
Keywords: machine-learning,multimodal,attention,pytorch,deep-learning,fusion
Classifier: Development Status :: 4 - Beta
Classifier: Intended Audience :: Developers
Classifier: Intended Audience :: Science/Research
Classifier: Operating System :: OS Independent
Classifier: Programming Language :: Python :: 3
Classifier: Programming Language :: Python :: 3.8
Classifier: Programming Language :: Python :: 3.9
Classifier: Programming Language :: Python :: 3.10
Classifier: Programming Language :: Python :: 3.11
Classifier: Programming Language :: Python :: 3.12
Classifier: Topic :: Scientific/Engineering :: Artificial Intelligence
Classifier: Topic :: Software Development :: Libraries :: Python Modules
Requires-Python: >=3.8
License-File: LICENSE
Requires-Dist: torch>=2.0.0
Requires-Dist: numpy
Dynamic: author
Dynamic: home-page
Dynamic: license-file
Dynamic: requires-python
